django_iprofile-0.0.1.dist-info/DESCRIPTION.rst
django_iprofile-0.0.1.dist-info/METADATA
django_iprofile-0.0.1.dist-info/RECORD
django_iprofile-0.0.1.dist-info/WHEEL
django_iprofile-0.0.1.dist-info/metadata.json
django_iprofile-0.0.1.dist-info/top_level.txt
iprofile_shell/__init__.py
iprofile_shell/management/__init__.py
iprofile_shell/management/commands/__init__.py
iprofile_shell/management/commands/ishell.py
