Metadata-Version: 2.0
Name: django-iprofile
Version: 0.0.1
Summary: A Django shell command to work with IProfile.
Home-page: https://github.com/victorfsf/django-iprofile
Author: Victor Ferraz
Author-email: victorfsf.dev@gmail.com
License: UNKNOWN
Keywords: ipython,python,python2,python3,shell,profile,iprofile,django
Platform: UNKNOWN
Classifier: Development Status :: 3 - Alpha
Classifier: Intended Audience :: Developers
Classifier: License :: OSI Approved :: GNU General Public License v3 (GPLv3)
Classifier: Programming Language :: Python :: 2
Classifier: Programming Language :: Python :: 2.7
Classifier: Programming Language :: Python :: 3
Classifier: Programming Language :: Python :: 3.3
Classifier: Programming Language :: Python :: 3.4
Classifier: Programming Language :: Python :: 3.5
Classifier: Framework :: Django :: 1.8
Classifier: Framework :: Django :: 1.9
Requires-Dist: python-iprofile
